gameyamlspiderandgenerator/__init__.py
gameyamlspiderandgenerator/__main__.py
gameyamlspiderandgenerator/exception.py
gameyamlspiderandgenerator/hook/__init__.py
gameyamlspiderandgenerator/hook/_base.py
gameyamlspiderandgenerator/plugin/__init__.py
gameyamlspiderandgenerator/plugin/_base.py
gameyamlspiderandgenerator/plugin/gcores.py
gameyamlspiderandgenerator/plugin/itchio.py
gameyamlspiderandgenerator/plugin/steam.py
gameyamlspiderandgenerator/util/__init__.py
gameyamlspiderandgenerator/util/config.py
gameyamlspiderandgenerator/util/fgi.py
gameyamlspiderandgenerator/util/fgi_yaml.py
gameyamlspiderandgenerator/util/plugin_manager.py
gameyamlspiderandgenerator/util/spider.py
gameyamlspiderandgenerator-2.1.2.dist-info/licenses/LICENSE
gameyamlspiderandgenerator-2.1.2.dist-info/METADATA
gameyamlspiderandgenerator-2.1.2.dist-info/WHEEL
gameyamlspiderandgenerator-2.1.2.dist-info/top_level.txt
gameyamlspiderandgenerator-2.1.2.dist-info/RECORD
