Metadata-Version: 2.4
Name: gameyamlspiderandgenerator
Version: 2.1.2
Summary: A useful tool for generating FurryGameIndex yaml files
Author: kaesinol
License: MIT
Project-URL: Homepage, https://github.com/FurryGamesIndex/GameYamlSpiderAndGenerator/
Classifier: Development Status :: 5 - Production/Stable
Classifier: Intended Audience :: Developers
Classifier: License :: OSI Approved :: MIT License
Classifier: Programming Language :: Python :: 3
Classifier: Programming Language :: Python :: 3.11
Classifier: Programming Language :: Python :: 3.12
Classifier: Programming Language :: Python :: 3.13
Classifier: Operating System :: OS Independent
Classifier: Operating System :: MacOS
Classifier: Operating System :: Microsoft :: Windows
Classifier: Operating System :: POSIX
Classifier: Topic :: Software Development :: Libraries :: Python Modules
Classifier: Topic :: Utilities
Classifier: Topic :: Text Processing
Classifier: Natural Language :: English
Classifier: Typing :: Typed
Requires-Python: <4.0,>=3.11
License-File: LICENSE
Requires-Dist: langcodes>=3.3.0
Requires-Dist: language-data<2.0,>=1.1
Requires-Dist: html2text>=2020.1.1
Requires-Dist: urllib3>=2.0
Requires-Dist: beautifulsoup4>=4.0
Requires-Dist: pillow>=10.0
Requires-Dist: ruamel-base>=1.0.0
Requires-Dist: loguru>=0.7.0
Requires-Dist: pyyaml>=6.0
Requires-Dist: pysocks>=1.7.1
Requires-Dist: lxml>=4.9.2
Requires-Dist: py3langid>=0.2.2
Requires-Dist: epicstore-api<1.0,>=0.1.7
Requires-Dist: deepdiff>=7.0.1
Requires-Dist: FGI-YAML-Formattor<1.0,>=0.1.0
Requires-Dist: yamlgenerator-hook-search<2.0,>=1.0.1
Requires-Dist: yamlgenerator-hook-validate<2.0,>=1.0.0a1
Requires-Dist: curl-cffi>=0.7.3
Requires-Dist: jq>=1.8.0
Provides-Extra: openai
Requires-Dist: yamlgenerator-hook-openai<2.0,>=1.0.0b; extra == "openai"
Dynamic: license-file
